[
  {
    "n": "芹菜炒五花肉",
    "d": "荤素结合",
    "c": "荤素结合",
    "e": "🍽️",
    "img": "images/grid_00_1.jpg"
  },
  {
    "n": "酸菜炒腊肠",
    "d": "荤素结合",
    "c": "荤素结合",
    "e": "🍽️",
    "img": "images/grid_00_2.jpg"
  },
  {
    "n": "鹿草菇炒腊肉",
    "d": "荤素结合",
    "c": "荤素结合",
    "e": "🍽️",
    "img": "images/grid_00_3.jpg"
  },
  {
    "n": "干豆角炒肉",
    "d": "荤素结合",
    "c": "荤素结合",
    "e": "🍽️",
    "img": "images/grid_00_4.jpg"
  },
  {
    "n": "咖喱牛肉",
    "d": "荤菜",
    "c": "荤菜",
    "e": "🍽️",
    "img": "images/grid_01_1.jpg"
  },
  {
    "n": "腊肠炒芹菜",
    "d": "荤素结合",
    "c": "荤素结合",
    "e": "🍽️",
    "img": "images/grid_01_2.jpg"
  },
  {
    "n": "青椒火腿炒鸡蛋",
    "d": "荤素结合",
    "c": "荤素结合",
    "e": "🍽️",
    "img": "images/grid_01_3.jpg"
  },
  {
    "n": "黄豆芽炒牛肉",
    "d": "荤菜",
    "c": "荤菜",
    "e": "🍽️",
    "img": "images/grid_01_4.jpg"
  },
  {
    "n": "糖醋排骨",
    "d": "荤菜",
    "c": "荤菜",
    "e": "🍽️",
    "img": "images/grid_02_1.jpg"
  },
  {
    "n": "香辣鸡翅",
    "d": "荤菜",
    "c": "荤菜",
    "e": "🍽️",
    "img": "images/grid_02_2.jpg"
  },
  {
    "n": "蒜苗回锅肉",
    "d": "荤菜",
    "c": "荤菜",
    "e": "🍽️",
    "img": "images/grid_02_3.jpg"
  },
  {
    "n": "肉沫茄子",
    "d": "荤素结合",
    "c": "荤素结合",
    "e": "🍽️",
    "img": "images/grid_02_4.jpg"
  },
  {
    "n": "葱爆五花肉",
    "d": "荤菜",
    "c": "荤菜",
    "e": "🍽️",
    "img": "images/grid_03_1.jpg"
  },
  {
    "n": "茄汁虾球",
    "d": "荤菜",
    "c": "荤菜",
    "e": "🍽️",
    "img": "images/grid_03_2.jpg"
  },
  {
    "n": "土豆烧牛肉丸",
    "d": "荤菜",
    "c": "荤菜",
    "e": "🍽️",
    "img": "images/grid_03_3.jpg"
  },
  {
    "n": "口蘑蒸蛋",
    "d": "荤素结合",
    "c": "荤素结合",
    "e": "🍽️",
    "img": "images/grid_03_4.jpg"
  },
  {
    "n": "洋葱肉沫炒鸡蛋",
    "d": "荤素结合",
    "c": "荤素结合",
    "e": "🍽️",
    "img": "images/grid_04_1.jpg"
  },
  {
    "n": "粉条炒芹菜",
    "d": "荤素结合",
    "c": "荤素结合",
    "e": "🍽️",
    "img": "images/grid_04_2.jpg"
  },
  {
    "n": "香菇炒火腿肠",
    "d": "荤素结合",
    "c": "荤素结合",
    "e": "🍽️",
    "img": "images/grid_04_3.jpg"
  },
  {
    "n": "平菇炒鸡蛋",
    "d": "荤素结合",
    "c": "荤素结合",
    "e": "🍽️",
    "img": "images/grid_04_4.jpg"
  },
  {
    "n": "肉沫腐竹",
    "d": "荤素结合",
    "c": "荤素结合",
    "e": "🍽️",
    "img": "images/grid_05_1.jpg"
  },
  {
    "n": "辣白菜炒年糕",
    "d": "荤素结合",
    "c": "荤素结合",
    "e": "🍽️",
    "img": "images/grid_05_2.jpg"
  },
  {
    "n": "番茄焖牛肉丸",
    "d": "荤菜",
    "c": "荤菜",
    "e": "🍽️",
    "img": "images/grid_05_3.jpg"
  },
  {
    "n": "咖喱鸡",
    "d": "荤菜",
    "c": "荤菜",
    "e": "🍽️",
    "img": "images/grid_05_4.jpg"
  },
  {
    "n": "娃娃菜焖油豆泡",
    "d": "素菜",
    "c": "素菜",
    "e": "🍽️",
    "img": "images/grid_06_1.jpg"
  },
  {
    "n": "香辣土豆片",
    "d": "素菜",
    "c": "素菜",
    "e": "🍽️",
    "img": "images/grid_06_2.jpg"
  },
  {
    "n": "鱼豆腐炒火腿",
    "d": "荤素结合",
    "c": "荤素结合",
    "e": "🍽️",
    "img": "images/grid_06_3.jpg"
  },
  {
    "n": "家常豆腐",
    "d": "素菜",
    "c": "素菜",
    "e": "🍽️",
    "img": "images/grid_06_4.jpg"
  },
  {
    "n": "芹菜炒虾仁",
    "d": "荤素结合",
    "c": "荤素结合",
    "e": "🍽️",
    "img": "images/grid_07_1.jpg"
  },
  {
    "n": "鸡毛菜炒香菇",
    "d": "荤素结合",
    "c": "荤素结合",
    "e": "🍽️",
    "img": "images/grid_07_2.jpg"
  },
  {
    "n": "沙葱炒鸡蛋",
    "d": "荤素结合",
    "c": "荤素结合",
    "e": "🍽️",
    "img": "images/grid_07_3.jpg"
  },
  {
    "n": "芹菜炒香干",
    "d": "荤素结合",
    "c": "荤素结合",
    "e": "🍽️",
    "img": "images/grid_07_4.jpg"
  },
  {
    "n": "油爆大虾",
    "d": "荤菜",
    "c": "荤菜",
    "e": "🍽️",
    "img": "images/grid_09_1.jpg"
  },
  {
    "n": "香菇滑鸡",
    "d": "荤素结合",
    "c": "荤素结合",
    "e": "🍽️",
    "img": "images/grid_09_2.jpg"
  },
  {
    "n": "蒜香口蘑鸡",
    "d": "荤素结合",
    "c": "荤素结合",
    "e": "🍽️",
    "img": "images/grid_09_3.jpg"
  },
  {
    "n": "麻婆豆腐",
    "d": "素菜",
    "c": "素菜",
    "e": "🍽️",
    "img": "images/grid_09_4.jpg"
  },
  {
    "n": "辣白菜炒五花肉",
    "d": "荤素结合",
    "c": "荤素结合",
    "e": "🍽️",
    "img": "images/grid_10_1.jpg"
  },
  {
    "n": "土豆炒蒜苔",
    "d": "素菜",
    "c": "素菜",
    "e": "🍽️",
    "img": "images/grid_10_2.jpg"
  },
  {
    "n": "土豆炒鸡肉",
    "d": "荤素结合",
    "c": "荤素结合",
    "e": "🍽️",
    "img": "images/grid_10_3.jpg"
  },
  {
    "n": "辣白菜炒土豆片",
    "d": "素菜",
    "c": "素菜",
    "e": "🍽️",
    "img": "images/grid_10_4.jpg"
  },
  {
    "n": "香菇烧豆腐",
    "d": "素菜",
    "c": "素菜",
    "e": "🍽️",
    "img": "images/grid_11_1.jpg"
  },
  {
    "n": "鱼香西葫芦",
    "d": "荤素结合",
    "c": "荤素结合",
    "e": "🍽️",
    "img": "images/grid_11_2.jpg"
  },
  {
    "n": "香菇炒青菜",
    "d": "素菜",
    "c": "素菜",
    "e": "🍽️",
    "img": "images/grid_11_3.jpg"
  },
  {
    "n": "茄汁包菜",
    "d": "素菜",
    "c": "素菜",
    "e": "🍽️",
    "img": "images/grid_11_4.jpg"
  },
  {
    "n": "鸡蛋炒粉条",
    "d": "荤素结合",
    "c": "荤素结合",
    "e": "🍽️",
    "img": "images/grid_12_1.jpg"
  },
  {
    "n": "火腿鸡蛋炒豆芽",
    "d": "荤素结合",
    "c": "荤素结合",
    "e": "🍽️",
    "img": "images/grid_12_2.jpg"
  },
  {
    "n": "牛肉丸炒鸡蛋",
    "d": "荤菜",
    "c": "荤菜",
    "e": "🍽️",
    "img": "images/grid_12_3.jpg"
  },
  {
    "n": "番茄肉沫炒蛋",
    "d": "荤素结合",
    "c": "荤素结合",
    "e": "🍽️",
    "img": "images/grid_12_4.jpg"
  },
  {
    "n": "鱼香鸡蛋",
    "d": "荤素结合",
    "c": "荤素结合",
    "e": "🍽️",
    "img": "images/grid_13_1.jpg"
  },
  {
    "n": "外婆菜炒鸡蛋",
    "d": "荤素结合",
    "c": "荤素结合",
    "e": "🍽️",
    "img": "images/grid_13_2.jpg"
  },
  {
    "n": "午餐肉炒土豆丝",
    "d": "荤素结合",
    "c": "荤素结合",
    "e": "🍽️",
    "img": "images/grid_13_3.jpg"
  },
  {
    "n": "番茄焖菜花",
    "d": "荤素结合",
    "c": "荤素结合",
    "e": "🍽️",
    "img": "images/grid_13_4.jpg"
  },
  {
    "n": "肉沫豆腐煲",
    "d": "荤素结合",
    "c": "荤素结合",
    "e": "🍽️",
    "img": "images/grid_14_1.jpg"
  },
  {
    "n": "酸汤小酥肉",
    "d": "荤菜",
    "c": "荤菜",
    "e": "🍽️",
    "img": "images/grid_14_2.jpg"
  },
  {
    "n": "香辣手撕鸡",
    "d": "荤菜",
    "c": "荤菜",
    "e": "🍽️",
    "img": "images/grid_14_3.jpg"
  },
  {
    "n": "腐竹焖荷包蛋",
    "d": "荤素结合",
    "c": "荤素结合",
    "e": "🍽️",
    "img": "images/grid_14_4.jpg"
  },
  {
    "n": "凉拌卤牛肉",
    "d": "凉拌菜",
    "c": "凉拌菜",
    "e": "🍽️",
    "img": "images/grid_15_1.jpg"
  },
  {
    "n": "凉拌油豆皮",
    "d": "凉拌菜",
    "c": "凉拌菜",
    "e": "🍽️",
    "img": "images/grid_15_2.jpg"
  },
  {
    "n": "凉拌包菜",
    "d": "凉拌菜",
    "c": "凉拌菜",
    "e": "🍽️",
    "img": "images/grid_15_3.jpg"
  },
  {
    "n": "炝拌香干丝",
    "d": "凉拌菜",
    "c": "凉拌菜",
    "e": "🍽️",
    "img": "images/grid_15_4.jpg"
  }
]